{"component":{"id":"AXPFX8bBNTPq5MfhO6--","key":"mynewsamplecsproj1","name":"mynewsamplecsproj1","qualifier":"TRK","measures":[{"metric":"alert_status","value":"ERROR"},{"metric":"quality_gate_details","value":"{\"level\":\"ERROR\",\"conditions\":[{\"metric\":\"new_reliability_rating\",\"op\":\"GT\",\"period\":1,\"error\":\"1\",\"actual\":\"4\",\"level\":\"ERROR\"},{\"metric\":\"new_security_rating\",\"op\":\"GT\",\"period\":1,\"error\":\"1\",\"actual\":\"1\",\"level\":\"OK\"},{\"metric\":\"new_maintainability_rating\",\"op\":\"GT\",\"period\":1,\"error\":\"1\",\"actual\":\"1\",\"level\":\"OK\"},{\"metric\":\"new_coverage\",\"op\":\"LT\",\"period\":1,\"error\":\"80\",\"actual\":\"0.32981530343007914\",\"level\":\"ERROR\"},{\"metric\":\"new_duplicated_lines_density\",\"op\":\"GT\",\"period\":1,\"error\":\"3\",\"actual\":\"1.1743750129450508\",\"level\":\"OK\"}],\"ignoredConditions\":false}"}],"branch":"SampleAssocaiteCode"}}